scabbard/Dax.py
scabbard/Dfig.py
scabbard/Dplot.py
scabbard/Dutils.py
scabbard/__init__.py
scabbard/_blandplot.py
scabbard/blendplot.py
scabbard/cli.py
scabbard/config.py
scabbard/enumeration.py
scabbard/environment.py
scabbard/evironment.py
scabbard/fastflood.py
scabbard/flow.py
scabbard/geography.py
scabbard/graphflood.py
scabbard/graphflood_helper.py
scabbard/grid.py
scabbard/gui_colormap_picker.py
scabbard/gui_float_sliders.py
scabbard/gui_load_file.py
scabbard/gui_main_window.py
scabbard/gui_maps_widgets.py
scabbard/gui_stylesheets.py
scabbard/gui_template.py
scabbard/haguid.py
scabbard/io.py
scabbard/legacy_graphflood.py
scabbard/lio.py
scabbard/local_file_picker.py
scabbard/nice_haguid.py
scabbard/nice_helper.py
scabbard/nice_utils.py
scabbard/phineas.py
scabbard/phineas_helper.py
scabbard/scabbard.py
scabbard/shape_functions.py
scabbard/utils.py
scabbard/_utils/__init__.py
scabbard/_utils/array_generators.py
scabbard/_utils/array_manipulations.py
scabbard/data/__init__.py
scabbard/data/config.json
scabbard/filter/__init__.py
scabbard/filter/spectral.py
scabbard/filters/__init__.py
scabbard/filters/spectral.py
scabbard/flow/LM.py
scabbard/flow/_LM.py
scabbard/flow/__init__.py
scabbard/flow/_bc_helper.py
scabbard/flow/bc_helper.py
scabbard/flow/drainage_area.py
scabbard/flow/flowdir.py
scabbard/flow/graph.py
scabbard/flow/rivnet.py
scabbard/geometry/__init__.py
scabbard/geometry/geometry.py
scabbard/geometry/regular_geometry.py
scabbard/graphflood/__init__.py
scabbard/graphflood/graphflood_interface.py
scabbard/graphflood_ui/__init__.py
scabbard/graphflood_ui/graphflood_interface.py
scabbard/graphflood_ui/grui_data.py
scabbard/io/__init__.py
scabbard/io/hdf5helper.py
scabbard/io/raster_loader.py
scabbard/raster/__init__.py
scabbard/raster/raster_factory.py
scabbard/raster/raster_grid.py
scabbard/raster/std_raster_cropper.py
scabbard/riverdale/__init__.py
scabbard/riverdale/rd_LM.py
scabbard/riverdale/rd_drainage_area.py
scabbard/riverdale/rd_env.py
pyscabbard-0.0.16.dist-info/AUTHORS.rst
pyscabbard-0.0.16.dist-info/LICENSE
pyscabbard-0.0.16.dist-info/METADATA
pyscabbard-0.0.16.dist-info/WHEEL
pyscabbard-0.0.16.dist-info/entry_points.txt
pyscabbard-0.0.16.dist-info/top_level.txt
pyscabbard-0.0.16.dist-info/RECORD
