Metadata-Version: 2.1
Name: pyscabbard
Version: 0.0.16
Summary: Suite of Hydrodynamic, topographic analysis, Landscape Evolution model and visualisation tools
Home-page: https://github.com/bgailleton/scabbard
Author: Boris Gailleton
Author-email: boris.gailleton@univ-rennes.fr
License: MIT license
Keywords: scabbard
Classifier: Development Status :: 4 - Beta
Classifier: License :: OSI Approved :: MIT License
Classifier: Natural Language :: English
Classifier: Programming Language :: Python :: 3
Classifier: Programming Language :: Python :: 3.10
Classifier: Programming Language :: Python :: 3.11
Classifier: Programming Language :: Python :: 3.12
Requires-Python: >=3.10
License-File: LICENSE
License-File: AUTHORS.rst
Requires-Dist: Click>=7.0
Requires-Dist: numpy>=2
Requires-Dist: numba>=0.60
Requires-Dist: daggerpy>=0.0.14
Requires-Dist: matplotlib
Requires-Dist: taichi
Requires-Dist: rasterio
Requires-Dist: scipy
Requires-Dist: cmcrameri
Requires-Dist: h5py
Requires-Dist: topotoolbox
